<?xml version = "1.0" encoding = "UTF-8" ?>
<mission id="assistant02" activeCheck="true" shouldIgnoreSenderVerification="false">
  <goals>
    <!-- Goals here -->
  </goals>
  <!-- 
  Add your mission start and end items here
  missionStart val="0">loadConditionalActions:Actions/TestActions.xml</missionStart>
  missionEnd val="1">addRank</missionEnd> 
  -->
  <missionStart val="1">addRankSilent</missionStart>
  <nextMission>NONE</nextMission>
  <!-- 
  <posting title="startingMission">This would be the post on a message board if it was on them.</posting>
  -->
  <email>
    <sender>Eleanor Hammond</sender>
    <subject>更新: 回合 3 基本情报</subject>
    <body>好的 #PLAYERNAME#,
看来你的技艺又更上一层了呢，这一次你要面对的黑客名为T4lisman。
      
根据他过去的经验和表现，我觉得他不会比你的上一个竞争者更有挑战性了。
我已经在他的电脑上跑了一个nmap，并正在看之前告诉你的那个SMTP端口。
      
他也设置了自定义端口，的确是个烦人玩意，
不过只要注意屏幕上看到的端口号，一切应该都没问题。
     
当你准备好的时候，就去战台领取任务吧。
    
 - Eleanor Hammond

Hacker Wars #PLAYERNAME#的助手
</body>
    <attachments>
      <!-- Add attachments like links and notes here -->
    </attachments>
  </email>
</mission>